phisherman/__init__.py
phisherman/errors.py
Phisherman-0.0.1.dist-info/METADATA
Phisherman-0.0.1.dist-info/WHEEL
Phisherman-0.0.1.dist-info/top_level.txt
Phisherman-0.0.1.dist-info/RECORD
