Metadata-Version: 2.1
Name: Phisherman
Version: 0.0.1
Summary: A simple synchronous API wrapper around Phisherman
Home-page: https://github.com/IlluminatiFish/Phisherman
Author: IlluminatiFish
License: Apache 2.0
Project-URL: Bug Tracker, https://github.com/IlluminatiFish/Phisherman/issues
Platform: UNKNOWN
Classifier: Programming Language :: Python :: 3
Requires-Dist: requests (>=2.23.0)
Requires-Dist: validators (>=0.18.2)
